azure/mgmt/extendedlocation/__init__.py
azure/mgmt/extendedlocation/_configuration.py
azure/mgmt/extendedlocation/_custom_locations.py
azure/mgmt/extendedlocation/_patch.py
azure/mgmt/extendedlocation/_serialization.py
azure/mgmt/extendedlocation/_version.py
azure/mgmt/extendedlocation/py.typed
azure/mgmt/extendedlocation/aio/__init__.py
azure/mgmt/extendedlocation/aio/_configuration.py
azure/mgmt/extendedlocation/aio/_custom_locations.py
azure/mgmt/extendedlocation/aio/_patch.py
azure/mgmt/extendedlocation/aio/operations/__init__.py
azure/mgmt/extendedlocation/aio/operations/_custom_locations_operations.py
azure/mgmt/extendedlocation/aio/operations/_patch.py
azure/mgmt/extendedlocation/models/__init__.py
azure/mgmt/extendedlocation/models/_custom_locations_enums.py
azure/mgmt/extendedlocation/models/_models_py3.py
azure/mgmt/extendedlocation/models/_patch.py
azure/mgmt/extendedlocation/operations/__init__.py
azure/mgmt/extendedlocation/operations/_custom_locations_operations.py
azure/mgmt/extendedlocation/operations/_patch.py
azure_mgmt_extendedlocation-2.0.0.dist-info/LICENSE
azure_mgmt_extendedlocation-2.0.0.dist-info/METADATA
azure_mgmt_extendedlocation-2.0.0.dist-info/WHEEL
azure_mgmt_extendedlocation-2.0.0.dist-info/top_level.txt
azure_mgmt_extendedlocation-2.0.0.dist-info/RECORD
